ansiterm/__init__.py
ansiterm-1.1.dist-info/LICENSE
ansiterm-1.1.dist-info/METADATA
ansiterm-1.1.dist-info/WHEEL
ansiterm-1.1.dist-info/top_level.txt
ansiterm-1.1.dist-info/RECORD
