Metadata-Version: 2.1
Name: ansiterm
Version: 1.1
Summary: change color and style (bold, reverse) of text on display
Home-page: https://github.com/h-ohsaki/ansiterm
Author: Hiroyuki Ohsaki
Author-email: ohsaki@lsnl.jp
License: UNKNOWN
Platform: UNKNOWN
Classifier: Programming Language :: Python :: 3
Classifier: License :: OSI Approved :: GNU General Public License v3 (GPLv3)
Classifier: Operating System :: OS Independent
